MANIFEST.in
README.rst
README.txt
gtarantool.py
setup.py
gtarantool.egg-info/PKG-INFO
gtarantool.egg-info/SOURCES.txt
gtarantool.egg-info/dependency_links.txt
gtarantool.egg-info/requires.txt
gtarantool.egg-info/top_level.txt