Metadata-Version: 1.1
Name: gtarantool
Version: 1.0.10
Summary: Tarantool connection driver for work with gevent framework
Home-page: https://github.com/shveenkov/gtarantool
Author: Dmitry Shveenkov
Author-email: shveenkov@mail.ru
License: UNKNOWN
Platform: UNKNOWN
Classifier: Programming Language :: Python
Classifier: Intended Audience :: Developers
Classifier: License :: OSI Approved :: GNU Library or Lesser General Public License (LGPL)
Classifier: Operating System :: OS Independent
Classifier: Topic :: Software Development :: Libraries :: Python Modules
Classifier: Topic :: Database :: Front-Ends
